rfb_mn_manager/__init__.py
rfb_mn_manager/__version__.py
rfb_mn_manager/context.py
rfb_mn_manager/mn_broker_client.py
rfb_mn_manager/mn_db_facade.py
rfb_mn_manager/mn_manager_node.py
rfb_mn_manager-1.0.4.dist-info/LICENSE.txt
rfb_mn_manager-1.0.4.dist-info/METADATA
rfb_mn_manager-1.0.4.dist-info/WHEEL
rfb_mn_manager-1.0.4.dist-info/top_level.txt
rfb_mn_manager-1.0.4.dist-info/RECORD
