Metadata-Version: 2.1
Name: rfb_mn_manager
Version: 1.0.4
Summary: Defines custom datatypes for use in cycler scripts related.
Author-email: Javier Sanz <javiersanzmoline+pypi@gmail.com>, Roberto Aldea <r.aldea.csic+pypi@gmail.com>, Marius Crisan <mariuscrsn+pypi@gmail.com>, Pablo Pastor <pastorpflores+pypi@gmail.com>, Luis Roche <luis.roche@hotmail.com>
Maintainer-email: Javier Sanz <javiersanzmoline+pypi@gmail.com>
License: GNU GENERAL PUBLIC LICENSE
Project-URL: Homepage, https://github.com/GIDEF-RFB/Battery-Experiments-Manager/
Project-URL: Bug Reports, https://github.com/GIDEF-RFB/Battery-Experiments-Manager/issues
Project-URL: Bug Tracker, https://github.com/GIDEF-RFB/Battery-Experiments-Manager/issues
Project-URL: Source, https://github.com/GIDEF-RFB/Battery-Experiments-Manager/tree/develop/mn_manager/src/rfb_mn_manager
Project-URL: Funding, https://donate.pypi.org
Keywords: manager,wattrex,cycler,mqtt,broker,database
Classifier: Development Status :: 3 - Alpha
Classifier: Topic :: Software Development :: Embedded Systems
Classifier: Operating System :: OS Independent
Classifier: License :: OSI Approved :: GNU Affero General Public License v3
Classifier: Programming Language :: Python :: 3
Classifier: Programming Language :: Python :: 3.7
Classifier: Programming Language :: Python :: 3.8
Classifier: Programming Language :: Python :: 3.9
Classifier: Programming Language :: Python :: 3.10
Classifier: Programming Language :: Python :: 3.11
Classifier: Programming Language :: Python :: 3 :: Only
Requires-Python: >=3.7
License-File: LICENSE.txt
Requires-Dist: rfb-logger-tool
Requires-Dist: rfb-shared-tool
Requires-Dist: rfb-cycler-datatypes
Requires-Dist: rfb-driver-mqtt
Requires-Dist: rfb-driver-db >=0.0.1
